Metadata-Version: 2.1
Name: zfs
Version: 0.0.1
Summary: Native Python wrapper for FreeBSD sysctls using libc.
Home-page: https://github.com/gronke/py-zfs
Author: Stefan Grönke
Author-email: stefan@gronke.net
License: UNKNOWN
Platform: UNKNOWN
Requires-Python: >=3.6
